flat_me/__init__.py
flat_me/file_factory.py
flat_me/pd_transformations.py
flat_me/user_prompt.py
flat_me/file_classes/__init__.py
flat_me/file_classes/csv_to_json.py
flat_me/file_classes/csv_to_txt.py
flat_me/file_classes/csv_utils.py
flat_me/file_classes/txt_to_csv.py
flat_me/file_classes/txt_to_json.py
flat_me/file_classes/txt_utils.py
flat_me-0.2.1.dist-info/LICENSE.txt
flat_me-0.2.1.dist-info/METADATA
flat_me-0.2.1.dist-info/WHEEL
flat_me-0.2.1.dist-info/entry_points.txt
flat_me-0.2.1.dist-info/top_level.txt
flat_me-0.2.1.dist-info/RECORD
