Metadata-Version: 2.1
Name: flat-me
Version: 0.2.1
Summary: File conversion/transformation tool
Author: uncomfortablepanda
License: Apache 2.0
Platform: UNKNOWN
License-File: LICENSE.txt
Requires-Dist: PyInquirer
Requires-Dist: pyfiglet
Requires-Dist: pandas
Requires-Dist: pathlib
